setup.py
replay_parser/__init__.py
replay_parser/replay_parser.py
replay_parser/tests.py
rocket_league_replay_parser.egg-info/PKG-INFO
rocket_league_replay_parser.egg-info/SOURCES.txt
rocket_league_replay_parser.egg-info/dependency_links.txt
rocket_league_replay_parser.egg-info/not-zip-safe
rocket_league_replay_parser.egg-info/top_level.txt