Metadata-Version: 1.1
Name: rocket-league-replay-parser
Version: 0.1.6
Summary: Parser for Rocket League replay files.
Home-page: https://github.com/danielsamuels/rocket-league-replay-parser
Author: Daniel Samuels
Author-email: daniel.samuels1@gmail.com
License: UNKNOWN
Platform: UNKNOWN
Classifier: Development Status :: 4 - Beta
Classifier: Intended Audience :: Developers
Classifier: Natural Language :: English
Classifier: Programming Language :: Python :: 2.7
Classifier: License :: OSI Approved :: GNU General Public License (GPL)
